{
  "code_commune": "62844",
  "commune": "Verchocq",
  "departement": "Pas-de-Calais",
  "tour": "T1",
  "maire": {
    "nom": "HUGUET",
    "prenom": "Patrick",
    "nom_complet": "Patrick HUGUET",
    "age": 55,
    "nuance": null
  },
  "resultats": {
    "inscrits": 541,
    "votants": 325,
    "pct_votants": 60.07,
    "abstentions": 216,
    "pct_abstentions": 39.93,
    "exprimes": 260
  },
  "listes": [
    {
      "num_panneau": "1",
      "libelle_liste": "VERCHOCQ ENSEMBLE",
      "libelle_abrege_liste": "VERCHOCQ ENSEMBLE",
      "nuance_liste": null,
      "voix": 260,
      "pct_voix_exprimes": 100,
      "sieges_cm": 15,
      "sieges_cc": null,
      "nb_elus": 15,
      "tete_de_liste": {
        "nom": "HUGUET",
        "prenom": "Patrick",
        "nom_complet": "Patrick HUGUET",
        "sexe": "M"
      },
      "elus": [
        {
          "nom": "HUGUET",
          "prenom": "Patrick",
          "nom_complet": "Patrick HUGUET",
          "sexe": "M",
          "age": 55,
          "rang_liste": "1"
        },
        {
          "nom": "DELAHAYE",
          "prenom": "Isabelle",
          "nom_complet": "Isabelle DELAHAYE",
          "sexe": "F",
          "age": 54,
          "rang_liste": "2"
        },
        {
          "nom": "LALOY",
          "prenom": "Raphaël",
          "nom_complet": "Raphaël LALOY",
          "sexe": "M",
          "age": 45,
          "rang_liste": "3"
        },
        {
          "nom": "MILON",
          "prenom": "Aurélie",
          "nom_complet": "Aurélie MILON",
          "sexe": "F",
          "age": 37,
          "rang_liste": "4"
        },
        {
          "nom": "LECHERF",
          "prenom": "Yannick",
          "nom_complet": "Yannick LECHERF",
          "sexe": "M",
          "age": 42,
          "rang_liste": "5"
        },
        {
          "nom": "DUCHATEL",
          "prenom": "Laurence",
          "nom_complet": "Laurence DUCHATEL",
          "sexe": "F",
          "age": 57,
          "rang_liste": "6"
        },
        {
          "nom": "RANDOUX",
          "prenom": "Maxime",
          "nom_complet": "Maxime RANDOUX",
          "sexe": "M",
          "age": 41,
          "rang_liste": "7"
        },
        {
          "nom": "LECERF",
          "prenom": "Jenny",
          "nom_complet": "Jenny LECERF",
          "sexe": "F",
          "age": 50,
          "rang_liste": "8"
        },
        {
          "nom": "PICHONNIER",
          "prenom": "Emeric",
          "nom_complet": "Emeric PICHONNIER",
          "sexe": "M",
          "age": 39,
          "rang_liste": "9"
        },
        {
          "nom": "FOUACHE",
          "prenom": "Audrey",
          "nom_complet": "Audrey FOUACHE",
          "sexe": "F",
          "age": 47,
          "rang_liste": "10"
        },
        {
          "nom": "DANEL",
          "prenom": "Jordan",
          "nom_complet": "Jordan DANEL",
          "sexe": "M",
          "age": 38,
          "rang_liste": "11"
        },
        {
          "nom": "BAILLY",
          "prenom": "Virginie",
          "nom_complet": "Virginie BAILLY",
          "sexe": "F",
          "age": 46,
          "rang_liste": "12"
        },
        {
          "nom": "SOCKEEL",
          "prenom": "Benjamin",
          "nom_complet": "Benjamin SOCKEEL",
          "sexe": "M",
          "age": 33,
          "rang_liste": "13"
        },
        {
          "nom": "BERTAUX",
          "prenom": "Céline",
          "nom_complet": "Céline BERTAUX",
          "sexe": "F",
          "age": 38,
          "rang_liste": "14"
        },
        {
          "nom": "CARPENTIER",
          "prenom": "Damien",
          "nom_complet": "Damien CARPENTIER",
          "sexe": "M",
          "age": 55,
          "rang_liste": "15"
        }
      ],
      "statut_conseil": "majorite"
    }
  ]
}